[
  {
    "inputs": [
      {
        "internalType": "uint256",
        "name": "_UIRMultiplier",
        "type": "uint256"
      },
      {
        "internalType": "uint256",
        "name": "_MinDepositPeriod",
        "type": "uint256"
      },
      {
        "internalType": "uint256",
        "name": "_MaxDepositAmount",
        "type": "uint256"
      },
      {
        "internalType": "address",
        "name": "_moneyMarket",
        "type": "address"
      },
      {
        "internalType": "address",
        "name": "_stablecoin",
        "type": "address"
      },
      {
        "internalType": "address",
        "name": "_feeModel",
        "type": "address"
      },
      {
        "internalType": "address",
        "name": "_depositNFT",
        "type": "address"
      },
      {
        "internalType": "address",
        "name": "_fundingNFT",
        "type": "address"
      }
    ],
    "payable": false,
    "stateMutability": "nonpayable",
    "type": "constructor"
  },
  {
    "anonymous": false,
    "inputs": [
      {
        "indexed": true,
        "internalType": "address",
        "name": "sender",
        "type": "address"
      },
      {
        "indexed": true,
        "internalType": "uint256",
        "name": "depositID",
        "type": "uint256"
      },
      {
        "indexed": false,
        "internalType": "uint256",
        "name": "amount",
        "type": "uint256"
      },
      {
        "indexed": false,
        "internalType": "uint256",
        "name": "maturationTimestamp",
        "type": "uint256"
      },
      {
        "indexed": false,
        "internalType": "uint256",
        "name": "upfrontInterestAmount",
        "type": "uint256"
      }
    ],
    "name": "EDeposit",
    "type": "event"
  },
  {
    "anonymous": false,
    "inputs": [
      {
        "indexed": true,
        "internalType": "address",
        "name": "sender",
        "type": "address"
      },
      {
        "indexed": true,
        "internalType": "uint256",
        "name": "fundingID",
        "type": "uint256"
      },
      {
        "indexed": false,
        "internalType": "uint256",
        "name": "deficitAmount",
        "type": "uint256"
      }
    ],
    "name": "EFund",
    "type": "event"
  },
  {
    "anonymous": false,
    "inputs": [
      {
        "indexed": true,
        "internalType": "address",
        "name": "sender",
        "type": "address"
      },
      {
        "indexed": true,
        "internalType": "uint256",
        "name": "depositID",
        "type": "uint256"
      },
      {
        "indexed": true,
        "internalType": "uint256",
        "name": "fundingID",
        "type": "uint256"
      },
      {
        "indexed": false,
        "internalType": "bool",
        "name": "early",
        "type": "bool"
      }
    ],
    "name": "EWithdraw",
    "type": "event"
  },
  {
    "constant": true,
    "inputs": [],
    "name": "MaxDepositAmount",
    "outputs": [
      {
        "internalType": "uint256",
        "name": "",
        "type": "uint256"
      }
    ],
    "payable": false,
    "stateMutability": "view",
    "type": "function"
  },
  {
    "constant": true,
    "inputs": [],
    "name": "MinDepositPeriod",
    "outputs": [
      {
        "internalType": "uint256",
        "name": "",
        "type": "uint256"
      }
    ],
    "payable": false,
    "stateMutability": "view",
    "type": "function"
  },
  {
    "constant": true,
    "inputs": [],
    "name": "UIRMultiplier",
    "outputs": [
      {
        "internalType": "uint256",
        "name": "",
        "type": "uint256"
      }
    ],
    "payable": false,
    "stateMutability": "view",
    "type": "function"
  },
  {
    "constant": true,
    "inputs": [],
    "name": "blocktime",
    "outputs": [
      {
        "internalType": "uint256",
        "name": "",
        "type": "uint256"
      }
    ],
    "payable": false,
    "stateMutability": "view",
    "type": "function"
  },
  {
    "constant": true,
    "inputs": [
      {
        "internalType": "uint256",
        "name": "depositPeriodInSeconds",
        "type": "uint256"
      }
    ],
    "name": "calculateUpfrontInterestRate",
    "outputs": [
      {
        "internalType": "uint256",
        "name": "upfrontInterestRate",
        "type": "uint256"
      }
    ],
    "payable": false,
    "stateMutability": "view",
    "type": "function"
  },
  {
    "constant": false,
    "inputs": [
      {
        "internalType": "uint256",
        "name": "amount",
        "type": "uint256"
      },
      {
        "internalType": "uint256",
        "name": "maturationTimestamp",
        "type": "uint256"
      }
    ],
    "name": "deposit",
    "outputs": [],
    "payable": false,
    "stateMutability": "nonpayable",
    "type": "function"
  },
  {
    "constant": true,
    "inputs": [
      {
        "internalType": "uint256",
        "name": "id",
        "type": "uint256"
      }
    ],
    "name": "depositIsFunded",
    "outputs": [
      {
        "internalType": "bool",
        "name": "",
        "type": "bool"
      }
    ],
    "payable": false,
    "stateMutability": "view",
    "type": "function"
  },
  {
    "constant": true,
    "inputs": [],
    "name": "depositNFT",
    "outputs": [
      {
        "internalType": "contract NFT",
        "name": "",
        "type": "address"
      }
    ],
    "payable": false,
    "stateMutability": "view",
    "type": "function"
  },
  {
    "constant": true,
    "inputs": [],
    "name": "depositsLength",
    "outputs": [
      {
        "internalType": "uint256",
        "name": "",
        "type": "uint256"
      }
    ],
    "payable": false,
    "stateMutability": "view",
    "type": "function"
  },
  {
    "constant": false,
    "inputs": [
      {
        "internalType": "uint256",
        "name": "depositID",
        "type": "uint256"
      },
      {
        "internalType": "uint256",
        "name": "fundingID",
        "type": "uint256"
      }
    ],
    "name": "earlyWithdraw",
    "outputs": [],
    "payable": false,
    "stateMutability": "nonpayable",
    "type": "function"
  },
  {
    "constant": true,
    "inputs": [],
    "name": "feeModel",
    "outputs": [
      {
        "internalType": "contract FeeModel",
        "name": "",
        "type": "address"
      }
    ],
    "payable": false,
    "stateMutability": "view",
    "type": "function"
  },
  {
    "constant": false,
    "inputs": [],
    "name": "fundAll",
    "outputs": [],
    "payable": false,
    "stateMutability": "nonpayable",
    "type": "function"
  },
  {
    "constant": false,
    "inputs": [
      {
        "internalType": "uint256",
        "name": "toDepositID",
        "type": "uint256"
      }
    ],
    "name": "fundMultiple",
    "outputs": [],
    "payable": false,
    "stateMutability": "nonpayable",
    "type": "function"
  },
  {
    "constant": true,
    "inputs": [],
    "name": "fundingListLength",
    "outputs": [
      {
        "internalType": "uint256",
        "name": "",
        "type": "uint256"
      }
    ],
    "payable": false,
    "stateMutability": "view",
    "type": "function"
  },
  {
    "constant": true,
    "inputs": [],
    "name": "fundingNFT",
    "outputs": [
      {
        "internalType": "contract NFT",
        "name": "",
        "type": "address"
      }
    ],
    "payable": false,
    "stateMutability": "view",
    "type": "function"
  },
  {
    "constant": true,
    "inputs": [
      {
        "internalType": "uint256",
        "name": "depositID",
        "type": "uint256"
      }
    ],
    "name": "getDeposit",
    "outputs": [
      {
        "components": [
          {
            "internalType": "uint256",
            "name": "amount",
            "type": "uint256"
          },
          {
            "internalType": "uint256",
            "name": "maturationTimestamp",
            "type": "uint256"
          },
          {
            "internalType": "uint256",
            "name": "initialDeficit",
            "type": "uint256"
          },
          {
            "internalType": "uint256",
            "name": "initialmoneyMarketIncomeIndex",
            "type": "uint256"
          },
          {
            "internalType": "bool",
            "name": "active",
            "type": "bool"
          },
          {
            "internalType": "bool",
            "name": "finalSurplusIsNegative",
            "type": "bool"
          },
          {
            "internalType": "uint256",
            "name": "finalSurplusAmount",
            "type": "uint256"
          }
        ],
        "internalType": "struct DInterest.Deposit",
        "name": "",
        "type": "tuple"
      }
    ],
    "payable": false,
    "stateMutability": "view",
    "type": "function"
  },
  {
    "constant": true,
    "inputs": [
      {
        "internalType": "uint256",
        "name": "fundingID",
        "type": "uint256"
      }
    ],
    "name": "getFunding",
    "outputs": [
      {
        "components": [
          {
            "internalType": "uint256",
            "name": "fromDepositID",
            "type": "uint256"
          },
          {
            "internalType": "uint256",
            "name": "toDepositID",
            "type": "uint256"
          },
          {
            "internalType": "uint256",
            "name": "recordedFundedDepositAmount",
            "type": "uint256"
          },
          {
            "internalType": "uint256",
            "name": "recordedMoneyMarketIncomeIndex",
            "type": "uint256"
          }
        ],
        "internalType": "struct DInterest.Funding",
        "name": "",
        "type": "tuple"
      }
    ],
    "payable": false,
    "stateMutability": "view",
    "type": "function"
  },
  {
    "constant": true,
    "inputs": [],
    "name": "latestFundedDepositID",
    "outputs": [
      {
        "internalType": "uint256",
        "name": "",
        "type": "uint256"
      }
    ],
    "payable": false,
    "stateMutability": "view",
    "type": "function"
  },
  {
    "constant": true,
    "inputs": [],
    "name": "moneyMarket",
    "outputs": [
      {
        "internalType": "contract IMoneyMarket",
        "name": "",
        "type": "address"
      }
    ],
    "payable": false,
    "stateMutability": "view",
    "type": "function"
  },
  {
    "constant": false,
    "inputs": [],
    "name": "moneyMarketIncomeIndex",
    "outputs": [
      {
        "internalType": "uint256",
        "name": "",
        "type": "uint256"
      }
    ],
    "payable": false,
    "stateMutability": "nonpayable",
    "type": "function"
  },
  {
    "constant": false,
    "inputs": [
      {
        "internalType": "uint256[]",
        "name": "amountList",
        "type": "uint256[]"
      },
      {
        "internalType": "uint256[]",
        "name": "maturationTimestampList",
        "type": "uint256[]"
      }
    ],
    "name": "multiDeposit",
    "outputs": [],
    "payable": false,
    "stateMutability": "nonpayable",
    "type": "function"
  },
  {
    "constant": false,
    "inputs": [
      {
        "internalType": "uint256[]",
        "name": "depositIDList",
        "type": "uint256[]"
      },
      {
        "internalType": "uint256[]",
        "name": "fundingIDList",
        "type": "uint256[]"
      }
    ],
    "name": "multiEarlyWithdraw",
    "outputs": [],
    "payable": false,
    "stateMutability": "nonpayable",
    "type": "function"
  },
  {
    "constant": false,
    "inputs": [
      {
        "internalType": "uint256[]",
        "name": "depositIDList",
        "type": "uint256[]"
      },
      {
        "internalType": "uint256[]",
        "name": "fundingIDList",
        "type": "uint256[]"
      }
    ],
    "name": "multiWithdraw",
    "outputs": [],
    "payable": false,
    "stateMutability": "nonpayable",
    "type": "function"
  },
  {
    "constant": true,
    "inputs": [],
    "name": "stablecoin",
    "outputs": [
      {
        "internalType": "contract ERC20",
        "name": "",
        "type": "address"
      }
    ],
    "payable": false,
    "stateMutability": "view",
    "type": "function"
  },
  {
    "constant": false,
    "inputs": [],
    "name": "surplus",
    "outputs": [
      {
        "internalType": "bool",
        "name": "isNegative",
        "type": "bool"
      },
      {
        "internalType": "uint256",
        "name": "surplusAmount",
        "type": "uint256"
      }
    ],
    "payable": false,
    "stateMutability": "nonpayable",
    "type": "function"
  },
  {
    "constant": false,
    "inputs": [
      {
        "internalType": "uint256",
        "name": "depositID",
        "type": "uint256"
      }
    ],
    "name": "surplusOfDeposit",
    "outputs": [
      {
        "internalType": "bool",
        "name": "isNegative",
        "type": "bool"
      },
      {
        "internalType": "uint256",
        "name": "surplusAmount",
        "type": "uint256"
      }
    ],
    "payable": false,
    "stateMutability": "nonpayable",
    "type": "function"
  },
  {
    "constant": true,
    "inputs": [],
    "name": "totalDeposit",
    "outputs": [
      {
        "internalType": "uint256",
        "name": "",
        "type": "uint256"
      }
    ],
    "payable": false,
    "stateMutability": "view",
    "type": "function"
  },
  {
    "constant": true,
    "inputs": [],
    "name": "unfundedUserDepositAmount",
    "outputs": [
      {
        "internalType": "uint256",
        "name": "",
        "type": "uint256"
      }
    ],
    "payable": false,
    "stateMutability": "view",
    "type": "function"
  },
  {
    "constant": false,
    "inputs": [
      {
        "internalType": "uint256",
        "name": "depositID",
        "type": "uint256"
      },
      {
        "internalType": "uint256",
        "name": "fundingID",
        "type": "uint256"
      }
    ],
    "name": "withdraw",
    "outputs": [],
    "payable": false,
    "stateMutability": "nonpayable",
    "type": "function"
  }
]